{
    "openapi": "3.0.0",
    "info": {
        "title": "",
        "description": "",
        "version": "0.0.0"
    },
    "servers": [
        {
            "url": "/",
            "description": ""
        }
    ],
    "paths": {
        "/api/authentication": {
            "post": {
                "operationId": "login_check_post",
                "tags": [
                    "Login Check"
                ],
                "responses": {
                    "200": {
                        "description": "User token created",
                        "content": {
                            "application/json": {
                                "schema": {
                                    "type": "object",
                                    "properties": {
                                        "token": {
                                            "readOnly": true,
                                            "type": "string",
                                            "nullable": false
                                        }
                                    },
                                    "required": [
                                        "token"
                                    ]
                                }
                            }
                        }
                    }
                },
                "summary": "Creates a user token.",
                "requestBody": {
                    "description": "The login data",
                    "content": {
                        "application/json": {
                            "schema": {
                                "type": "object",
                                "properties": {
                                    "email": {
                                        "type": "string",
                                        "nullable": false
                                    },
                                    "password": {
                                        "type": "string",
                                        "nullable": false
                                    }
                                },
                                "required": [
                                    "email",
                                    "password"
                                ]
                            }
                        }
                    },
                    "required": true
                }
            },
            "parameters": []
        },
        "/api/user/me": {
            "get": {
                "operationId": "api_userme_get",
                "tags": [
                    "User"
                ],
                "responses": {
                    "200": {
                        "description": "User resource me",
                        "content": {
                            "application/json": {
                                "schema": {
                                    "$ref": "#/components/schemas/User-default"
                                }
                            }
                        }
                    },
                    "401": {
                        "description": "Unauthorized"
                    }
                },
                "summary": "User resource me",
                "description": "User resource me",
                "parameters": [],
                "deprecated": false
            },
            "parameters": []
        }
    },
    "components": {
        "schemas": {
            "User-default": {
                "type": "object",
                "description": "",
                "deprecated": false
            },
            "User.jsonld-default": {
                "type": "object",
                "description": "",
                "deprecated": false,
                "properties": {
                    "@context": {
                        "readOnly": true,
                        "oneOf": [
                            {
                                "type": "string"
                            },
                            {
                                "type": "object",
                                "properties": {
                                    "@vocab": {
                                        "type": "string"
                                    },
                                    "hydra": {
                                        "type": "string",
                                        "enum": [
                                            "http://www.w3.org/ns/hydra/core#"
                                        ]
                                    }
                                },
                                "required": [
                                    "@vocab",
                                    "hydra"
                                ],
                                "additionalProperties": true
                            }
                        ]
                    },
                    "@id": {
                        "readOnly": true,
                        "type": "string"
                    },
                    "@type": {
                        "readOnly": true,
                        "type": "string"
                    }
                }
            }
        },
        "responses": {},
        "parameters": {},
        "examples": {},
        "requestBodies": {},
        "headers": {},
        "securitySchemes": {
            "JWT": {
                "type": "apiKey",
                "description": "Value for the Authorization header parameter.",
                "name": "Authorization",
                "in": "header"
            }
        }
    },
    "security": [
        {
            "JWT": []
        }
    ],
    "tags": []
}
2023-05-20T09:42:52+00:00 [info] User Deprecated: Since api-platform/core 3.1: The "openapiContext" option is deprecated, use "openapi" instead.
2023-05-20T09:42:52+00:00 [info] User Deprecated: Since api-platform/core 3.1: The "openapiContext" option is deprecated, use "openapi" instead.
2023-05-20T09:42:52+00:00 [info] User Deprecated: Since api-platform/core 3.1: The "openapiContext" option is deprecated, use "openapi" instead.
2023-05-20T09:42:52+00:00 [info] User Deprecated: Since api-platform/core 3.1: The "openapiContext" option is deprecated, use "openapi" instead.
